LICENSE
README.md
pyproject.toml
setup.py
pax/__init__.py
pax/experiment.py
pax/runner_eval.py
pax/runner_evo.py
pax/runner_marl.py
pax/runner_sarl.py
pax/utils.py
pax/version.py
pax/watchers.py
pax_rl.egg-info/PKG-INFO
pax_rl.egg-info/SOURCES.txt
pax_rl.egg-info/dependency_links.txt
pax_rl.egg-info/requires.txt
pax_rl.egg-info/top_level.txt
test/test_strategies.py