Metadata-Version: 2.1
Name: pax-rl
Version: 0.1.0b0
Summary: Pax: Environment for ...
Home-page: https://github.com/akbir/pax
Author: Akbir Khan
License: Apache License, Version 2.0
Platform: UNKNOWN
Classifier: License :: OSI Approved :: Apache Software License
Classifier: Development Status :: 4 - Beta
Classifier: Operating System :: POSIX :: Linux
Classifier: Operating System :: MacOS
Classifier: Programming Language :: Python :: 3
Classifier: Programming Language :: Python :: 3.9
Classifier: Topic :: Scientific/Engineering :: Artificial Intelligence
Classifier: Topic :: Games/Entertainment
Requires-Python: >=3.9
Provides-Extra: dev
License-File: LICENSE
